whitebox_plugin_gps_display/__init__.py
whitebox_plugin_gps_display/jsx/Map.jsx
whitebox_plugin_gps_display/jsx/WhiteboxMarker.jsx
whitebox_plugin_gps_display/jsx/stores/map.js
whitebox_plugin_gps_display/jsx/stores/map.test.js
whitebox_plugin_gps_display/jsx/utils/leaflet_patch.js
whitebox_plugin_gps_display/whitebox_plugin_gps_display.py
whitebox_test_plugin_gps_display/__init__.py
whitebox_test_plugin_gps_display/federation/map.spec.js
whitebox_test_plugin_gps_display/federation/whitebox_marker.spec.js
whitebox_test_plugin_gps_display/test_whitebox_plugin_gps_display.py
whitebox_plugin_gps_display-0.1.15.dist-info/LICENSE
whitebox_plugin_gps_display-0.1.15.dist-info/METADATA
whitebox_plugin_gps_display-0.1.15.dist-info/WHEEL
whitebox_plugin_gps_display-0.1.15.dist-info/RECORD
